setup.py
timetoolkit/__init__.py
timetoolkit.egg-info/PKG-INFO
timetoolkit.egg-info/SOURCES.txt
timetoolkit.egg-info/dependency_links.txt
timetoolkit.egg-info/top_level.txt