Metadata-Version: 1.0
Name: timetoolkit
Version: 2.0
Summary: Some great tools about time.
Home-page: https://github.com
Author: 张乐涛
Author-email: 1668151593@qq.com
License: UNKNOWN
Platform: UNKNOWN
